LICENSE
README.md
setup.py
ooj/__init__.py
ooj/base.py
ooj/entities.py
ooj/field.py
ooj/file.py
ooj/schema.py
ooj/serializer.py
ooj/url.py
ooj.egg-info/PKG-INFO
ooj.egg-info/SOURCES.txt
ooj.egg-info/dependency_links.txt
ooj.egg-info/requires.txt
ooj.egg-info/top_level.txt
ooj/exceptions/__init__.py
ooj/exceptions/exceptions.py
tests/test_json_file.py
tests/test_serializer.py