Metadata-Version: 2.1
Name: ooj
Version: 0.1.1
Summary: Object-Oriented JSON (OOJ) is a universal libraryfor working with JSON in Python, providing simplicityand convenience in serializing and deserializingcomplex objects.
Home-page: https://github.com/KiryxaTechDev/ooj
Download-URL: https://github.com/KiryxaTechDev/ooj/archive/refs/tags/0.1.1.zip
Author: KiryxaTech
Author-email: kiryxatech@gmail.com
Classifier: License :: OSI Approved :: Apache Software License
Classifier: Programming Language :: Python
Classifier: Programming Language :: Python :: 3
Classifier: Programming Language :: Python :: 3.1
Classifier: Programming Language :: Python :: 3.2
Classifier: Programming Language :: Python :: 3.3
Classifier: Programming Language :: Python :: 3.4
Classifier: Programming Language :: Python :: 3.5
Classifier: Programming Language :: Python :: 3.6
Classifier: Programming Language :: Python :: 3.7
Classifier: Programming Language :: Python :: 3.8
Classifier: Programming Language :: Python :: 3.9
Classifier: Programming Language :: Python :: 3.10
Classifier: Programming Language :: Python :: 3.11
Classifier: Programming Language :: Python :: 3.12
License-File: LICENSE
Requires-Dist: jsonschema>=4.0.0
Requires-Dist: requests==2.32.3
